{
  "id": "github-sakura-ku-grobal-mcp-stock-server-8b2a518d",
  "name": "sakura-ku/grobal_mcp_stock_server",
  "description": "Facilitates real-time access to global stock market data and analysis for AI assistants.",
  "category": "Finance & Crypto",
  "profileUrl": "https://tensorblock.co/mcp/github-sakura-ku-grobal-mcp-stock-server-8b2a518d",
  "badgeMarkdown": "[![Listed on TensorBlock MCP Index](https://img.shields.io/badge/TensorBlock-MCP%20Index-blue)](https://tensorblock.co/mcp/github-sakura-ku-grobal-mcp-stock-server-8b2a518d)",
  "links": {
    "primary": "https://github.com/sakura-ku/grobal_mcp_stock_server",
    "repo": "https://github.com/sakura-ku/grobal_mcp_stock_server",
    "homepage": null,
    "docs": null,
    "endpoint": null
  },
  "summary": {
    "transport": [
      "unknown"
    ],
    "auth": "unknown",
    "installConfidence": "low",
    "verification": "unknown",
    "toolCount": null
  }
}
