{
  "id": "github-amp-labs-sdk-node-platform-76a58c62",
  "name": "amp-labs/sdk-node-platform",
  "description": "A declarative platform SDK for SaaS builders, enabling seamless product integrations with MCP server capabilities for AI applications.",
  "category": "Frameworks",
  "profileUrl": "https://tensorblock.co/mcp/github-amp-labs-sdk-node-platform-76a58c62",
  "badgeMarkdown": "[![Listed on TensorBlock MCP Index](https://img.shields.io/badge/TensorBlock-MCP%20Index-blue)](https://tensorblock.co/mcp/github-amp-labs-sdk-node-platform-76a58c62)",
  "links": {
    "primary": "https://github.com/amp-labs/sdk-node-platform",
    "repo": "https://github.com/amp-labs/sdk-node-platform",
    "homepage": null,
    "docs": null,
    "endpoint": null
  },
  "summary": {
    "transport": [
      "unknown"
    ],
    "auth": "unknown",
    "installConfidence": "low",
    "verification": "unknown",
    "toolCount": null
  }
}
