{
  "id": "github-dragomiralin-openstack-mcp-server-5cccf215",
  "name": "DragomirAlin/openstack-mcp-server",
  "description": "Facilitates secure execution of OpenStack CLI commands through AI assistants using the Model Context Protocol.",
  "category": "Cloud Platforms & Services",
  "profileUrl": "https://tensorblock.co/mcp/github-dragomiralin-openstack-mcp-server-5cccf215",
  "badgeMarkdown": "[![Listed on TensorBlock MCP Index](https://img.shields.io/badge/TensorBlock-MCP%20Index-blue)](https://tensorblock.co/mcp/github-dragomiralin-openstack-mcp-server-5cccf215)",
  "links": {
    "primary": "https://github.com/DragomirAlin/openstack-mcp-server",
    "repo": "https://github.com/DragomirAlin/openstack-mcp-server",
    "homepage": null,
    "docs": null,
    "endpoint": null
  },
  "summary": {
    "transport": [
      "unknown"
    ],
    "auth": "unknown",
    "installConfidence": "low",
    "verification": "unknown",
    "toolCount": null
  }
}
