{
  "id": "github-deepsuthar496-figma-mcp-server-235c3c22",
  "name": "deepsuthar496/figma-mcp-server",
  "description": "Facilitates seamless interaction with Figma's API for managing files, comments, projects, and webhooks.",
  "category": "Developer Productivity & Utilities",
  "profileUrl": "https://tensorblock.co/mcp/github-deepsuthar496-figma-mcp-server-235c3c22",
  "badgeMarkdown": "[![Listed on TensorBlock MCP Index](https://img.shields.io/badge/TensorBlock-MCP%20Index-blue)](https://tensorblock.co/mcp/github-deepsuthar496-figma-mcp-server-235c3c22)",
  "links": {
    "primary": "https://github.com/deepsuthar496/figma-mcp-server",
    "repo": "https://github.com/deepsuthar496/figma-mcp-server",
    "homepage": null,
    "docs": null,
    "endpoint": null
  },
  "summary": {
    "transport": [
      "unknown"
    ],
    "auth": "unknown",
    "installConfidence": "low",
    "verification": "unknown",
    "toolCount": null
  }
}
