{
  "id": "github-yanceyofficial-obsidian-mcp-097a2189",
  "name": "YanceyOfficial/obsidian-mcp",
  "description": "Facilitates AI integration with Obsidian Vaults stored in iCloud using the Model Context Protocol.",
  "category": "Knowledge Management & Memory",
  "profileUrl": "https://tensorblock.co/mcp/github-yanceyofficial-obsidian-mcp-097a2189",
  "badgeMarkdown": "[![Listed on TensorBlock MCP Index](https://img.shields.io/badge/TensorBlock-MCP%20Index-blue)](https://tensorblock.co/mcp/github-yanceyofficial-obsidian-mcp-097a2189)",
  "links": {
    "primary": "https://github.com/YanceyOfficial/obsidian-mcp",
    "repo": "https://github.com/YanceyOfficial/obsidian-mcp",
    "homepage": null,
    "docs": null,
    "endpoint": null
  },
  "summary": {
    "transport": [
      "unknown"
    ],
    "auth": "unknown",
    "installConfidence": "low",
    "verification": "unknown",
    "toolCount": null
  }
}
