{
  "id": "github-zxreaper-cookbook-mcp-server-72097367",
  "name": "ZXreaper/cookbook-mcp-server",
  "description": "Facilitates access to a comprehensive cookbook through MCP server functionalities, enabling retrieval of all recipes or specific dish instructions.",
  "category": "Utilities & Helpers",
  "profileUrl": "https://tensorblock.co/mcp/github-zxreaper-cookbook-mcp-server-72097367",
  "badgeMarkdown": "[![Listed on TensorBlock MCP Index](https://img.shields.io/badge/TensorBlock-MCP%20Index-blue)](https://tensorblock.co/mcp/github-zxreaper-cookbook-mcp-server-72097367)",
  "links": {
    "primary": "https://github.com/ZXreaper/cookbook-mcp-server",
    "repo": "https://github.com/ZXreaper/cookbook-mcp-server",
    "homepage": null,
    "docs": null,
    "endpoint": null
  },
  "summary": {
    "transport": [
      "unknown"
    ],
    "auth": "unknown",
    "installConfidence": "low",
    "verification": "unknown",
    "toolCount": null
  }
}
