{
  "id": "github-focussearch-focus-mcp-sql-46f29540",
  "name": "FocusSearch/focus_mcp_sql",
  "description": "FocusSearch's MCP server transforms natural language into SQL queries with enhanced accuracy and speed through a two-step keyword parsing approach.",
  "category": "Data Analysis & Business Intelligence",
  "profileUrl": "https://tensorblock.co/mcp/github-focussearch-focus-mcp-sql-46f29540",
  "badgeMarkdown": "[![Listed on TensorBlock MCP Index](https://img.shields.io/badge/TensorBlock-MCP%20Index-blue)](https://tensorblock.co/mcp/github-focussearch-focus-mcp-sql-46f29540)",
  "links": {
    "primary": "https://github.com/FocusSearch/focus_mcp_sql",
    "repo": "https://github.com/FocusSearch/focus_mcp_sql",
    "homepage": null,
    "docs": null,
    "endpoint": null
  },
  "summary": {
    "transport": [
      "sse"
    ],
    "auth": "unknown",
    "installConfidence": "low",
    "verification": "unknown",
    "toolCount": null
  }
}
