{
  "id": "github-sammcj-bybit-mcp-69c89b2b",
  "name": "sammcj/bybit-mcp",
  "description": "Provides read-only access to Bybit's cryptocurrency exchange API, enabling real-time data retrieval and interaction with trading tools.",
  "category": "Finance & Crypto",
  "profileUrl": "https://tensorblock.co/mcp/github-sammcj-bybit-mcp-69c89b2b",
  "badgeMarkdown": "[![Listed on TensorBlock MCP Index](https://img.shields.io/badge/TensorBlock-MCP%20Index-blue)](https://tensorblock.co/mcp/github-sammcj-bybit-mcp-69c89b2b)",
  "links": {
    "primary": "https://github.com/sammcj/bybit-mcp",
    "repo": "https://github.com/sammcj/bybit-mcp",
    "homepage": null,
    "docs": null,
    "endpoint": null
  },
  "summary": {
    "transport": [
      "unknown"
    ],
    "auth": "unknown",
    "installConfidence": "low",
    "verification": "unknown",
    "toolCount": null
  }
}
