{
  "id": "github-delano-postman-mcp-server-14267b1a",
  "name": "delano/postman-mcp-server",
  "description": "Integrates with the Postman API to manage collections, environments, and APIs using the Model Context Protocol.",
  "category": "Developer Productivity & Utilities",
  "profileUrl": "https://tensorblock.co/mcp/github-delano-postman-mcp-server-14267b1a",
  "badgeMarkdown": "[![Listed on TensorBlock MCP Index](https://img.shields.io/badge/TensorBlock-MCP%20Index-blue)](https://tensorblock.co/mcp/github-delano-postman-mcp-server-14267b1a)",
  "links": {
    "primary": "https://github.com/delano/postman-mcp-server",
    "repo": "https://github.com/delano/postman-mcp-server",
    "homepage": null,
    "docs": null,
    "endpoint": null
  },
  "summary": {
    "transport": [
      "unknown"
    ],
    "auth": "unknown",
    "installConfidence": "low",
    "verification": "unknown",
    "toolCount": null
  }
}
