{
  "id": "github-n0el4kls-burpmcp-ee04e991",
  "name": "N0el4kLs/BurpMCP",
  "description": "Facilitates data retrieval from Burp Suite's proxy history for enhanced security testing and analysis.",
  "category": "Security",
  "profileUrl": "https://tensorblock.co/mcp/github-n0el4kls-burpmcp-ee04e991",
  "badgeMarkdown": "[![Listed on TensorBlock MCP Index](https://img.shields.io/badge/TensorBlock-MCP%20Index-blue)](https://tensorblock.co/mcp/github-n0el4kls-burpmcp-ee04e991)",
  "links": {
    "primary": "https://github.com/N0el4kLs/BurpMCP",
    "repo": "https://github.com/N0el4kLs/BurpMCP",
    "homepage": null,
    "docs": null,
    "endpoint": null
  },
  "summary": {
    "transport": [
      "unknown"
    ],
    "auth": "unknown",
    "installConfidence": "low",
    "verification": "unknown",
    "toolCount": null
  }
}
