{
  "id": "github-masacento-mcp-go-example-e861b99a",
  "name": "masacento/mcp-go-example",
  "description": "A Go-based example server for the Model Context Protocol, designed for educational purposes with no security or multiuser support.",
  "category": "Frameworks",
  "profileUrl": "https://tensorblock.co/mcp/github-masacento-mcp-go-example-e861b99a",
  "badgeMarkdown": "[![Listed on TensorBlock MCP Index](https://img.shields.io/badge/TensorBlock-MCP%20Index-blue)](https://tensorblock.co/mcp/github-masacento-mcp-go-example-e861b99a)",
  "links": {
    "primary": "https://github.com/masacento/mcp-go-example",
    "repo": "https://github.com/masacento/mcp-go-example",
    "homepage": null,
    "docs": null,
    "endpoint": null
  },
  "summary": {
    "transport": [
      "unknown"
    ],
    "auth": "unknown",
    "installConfidence": "low",
    "verification": "unknown",
    "toolCount": null
  }
}
