{
  "id": "github-frankgoortani-cv-mcp-a8dcfd68",
  "name": "FrankGoortani/cv-mcp",
  "description": "A specialized MCP server offering structured access to Frank Goortani's CV data for AI assistants and MCP-compatible clients.",
  "category": "Knowledge Management & Memory",
  "profileUrl": "https://tensorblock.co/mcp/github-frankgoortani-cv-mcp-a8dcfd68",
  "badgeMarkdown": "[![Listed on TensorBlock MCP Index](https://img.shields.io/badge/TensorBlock-MCP%20Index-blue)](https://tensorblock.co/mcp/github-frankgoortani-cv-mcp-a8dcfd68)",
  "links": {
    "primary": "https://github.com/FrankGoortani/cv-mcp",
    "repo": "https://github.com/FrankGoortani/cv-mcp",
    "homepage": null,
    "docs": null,
    "endpoint": null
  },
  "summary": {
    "transport": [
      "unknown"
    ],
    "auth": "unknown",
    "installConfidence": "low",
    "verification": "unknown",
    "toolCount": null
  }
}
