{
  "id": "github-leopeng1995-mysql-mcp-server-b9c1a089",
  "name": "leopeng1995/mysql-mcp-server",
  "description": "Facilitates seamless integration with MySQL databases using the Model Context Protocol.",
  "category": "Databases",
  "profileUrl": "https://tensorblock.co/mcp/github-leopeng1995-mysql-mcp-server-b9c1a089",
  "badgeMarkdown": "[![Listed on TensorBlock MCP Index](https://img.shields.io/badge/TensorBlock-MCP%20Index-blue)](https://tensorblock.co/mcp/github-leopeng1995-mysql-mcp-server-b9c1a089)",
  "links": {
    "primary": "https://github.com/leopeng1995/mysql-mcp-server",
    "repo": "https://github.com/leopeng1995/mysql-mcp-server",
    "homepage": null,
    "docs": null,
    "endpoint": null
  },
  "summary": {
    "transport": [
      "unknown"
    ],
    "auth": "unknown",
    "installConfidence": "low",
    "verification": "unknown",
    "toolCount": null
  }
}
