{
  "id": "github-bsmi021-mcp-python-executor-ae909795",
  "name": "bsmi021/mcp-python-executor",
  "description": "Facilitates secure Python code execution and package management with resource monitoring and logging capabilities.",
  "category": "Code Execution",
  "profileUrl": "https://tensorblock.co/mcp/github-bsmi021-mcp-python-executor-ae909795",
  "badgeMarkdown": "[![Listed on TensorBlock MCP Index](https://img.shields.io/badge/TensorBlock-MCP%20Index-blue)](https://tensorblock.co/mcp/github-bsmi021-mcp-python-executor-ae909795)",
  "links": {
    "primary": "https://github.com/bsmi021/mcp-python-executor",
    "repo": "https://github.com/bsmi021/mcp-python-executor",
    "homepage": null,
    "docs": null,
    "endpoint": null
  },
  "summary": {
    "transport": [
      "unknown"
    ],
    "auth": "unknown",
    "installConfidence": "low",
    "verification": "unknown",
    "toolCount": null
  }
}
