{
  "id": "github-andriichumak-gooddata-mcp-b3b55275",
  "name": "andriichumak/gooddata-mcp",
  "description": "Facilitates semantic search, visualization generation, and email report scheduling for GoodData using MCP.",
  "category": "Data Analysis & Business Intelligence",
  "profileUrl": "https://tensorblock.co/mcp/github-andriichumak-gooddata-mcp-b3b55275",
  "badgeMarkdown": "[![Listed on TensorBlock MCP Index](https://img.shields.io/badge/TensorBlock-MCP%20Index-blue)](https://tensorblock.co/mcp/github-andriichumak-gooddata-mcp-b3b55275)",
  "links": {
    "primary": "https://github.com/andriichumak/gooddata-mcp",
    "repo": "https://github.com/andriichumak/gooddata-mcp",
    "homepage": null,
    "docs": null,
    "endpoint": null
  },
  "summary": {
    "transport": [
      "unknown"
    ],
    "auth": "unknown",
    "installConfidence": "low",
    "verification": "unknown",
    "toolCount": null
  }
}
