{
  "id": "github-aaryash-shakya-mcp-servers-66303b43",
  "name": "Aaryash-Shakya/mcp-servers",
  "description": "Utilize TypeScript SDK to develop versatile MCP servers for various applications.",
  "category": "Developer Productivity & Utilities",
  "profileUrl": "https://tensorblock.co/mcp/github-aaryash-shakya-mcp-servers-66303b43",
  "badgeMarkdown": "[![Listed on TensorBlock MCP Index](https://img.shields.io/badge/TensorBlock-MCP%20Index-blue)](https://tensorblock.co/mcp/github-aaryash-shakya-mcp-servers-66303b43)",
  "links": {
    "primary": "https://github.com/Aaryash-Shakya/mcp-servers",
    "repo": "https://github.com/Aaryash-Shakya/mcp-servers",
    "homepage": null,
    "docs": null,
    "endpoint": null
  },
  "summary": {
    "transport": [
      "unknown"
    ],
    "auth": "unknown",
    "installConfidence": "low",
    "verification": "unknown",
    "toolCount": null
  }
}
