{
  "id": "github-shopsavvy-shopsavvy-mcp-server-faa732f0",
  "name": "shopsavvy/shopsavvy-mcp-server",
  "description": "Real-time product pricing, price history, and shopping tools across thousands of retailers. Free tier, no signup required.",
  "category": "Search",
  "profileUrl": "https://tensorblock.co/mcp/github-shopsavvy-shopsavvy-mcp-server-faa732f0",
  "badgeMarkdown": "[![Listed on TensorBlock MCP Index](https://img.shields.io/badge/TensorBlock-MCP%20Index-blue)](https://tensorblock.co/mcp/github-shopsavvy-shopsavvy-mcp-server-faa732f0)",
  "links": {
    "primary": "https://github.com/shopsavvy/shopsavvy-mcp-server",
    "repo": "https://github.com/shopsavvy/shopsavvy-mcp-server",
    "homepage": null,
    "docs": null,
    "endpoint": null
  },
  "summary": {
    "transport": [
      "unknown"
    ],
    "auth": "unknown",
    "installConfidence": "low",
    "verification": "unknown",
    "toolCount": null
  }
}
