{
  "id": "github-stevengonsalvez-mcp-todoist-4357e361",
  "name": "stevengonsalvez/mcp-todoist",
  "description": "Integrates Todoist with language models for seamless task management through natural language commands.",
  "category": "Project & Task Management",
  "profileUrl": "https://tensorblock.co/mcp/github-stevengonsalvez-mcp-todoist-4357e361",
  "badgeMarkdown": "[![Listed on TensorBlock MCP Index](https://img.shields.io/badge/TensorBlock-MCP%20Index-blue)](https://tensorblock.co/mcp/github-stevengonsalvez-mcp-todoist-4357e361)",
  "links": {
    "primary": "https://github.com/stevengonsalvez/mcp-todoist",
    "repo": "https://github.com/stevengonsalvez/mcp-todoist",
    "homepage": null,
    "docs": null,
    "endpoint": null
  },
  "summary": {
    "transport": [
      "unknown"
    ],
    "auth": "unknown",
    "installConfidence": "low",
    "verification": "unknown",
    "toolCount": null
  }
}
