{
  "id": "github-bourbonkk-k8s-pilot-768bdf7a",
  "name": "bourbonkk/k8s-pilot",
  "description": "Centralized control plane server for managing multiple Kubernetes clusters with intuitive APIs and multi-cluster context switching.",
  "category": "Infrastructure",
  "profileUrl": "https://tensorblock.co/mcp/github-bourbonkk-k8s-pilot-768bdf7a",
  "badgeMarkdown": "[![Listed on TensorBlock MCP Index](https://img.shields.io/badge/TensorBlock-MCP%20Index-blue)](https://tensorblock.co/mcp/github-bourbonkk-k8s-pilot-768bdf7a)",
  "links": {
    "primary": "https://github.com/bourbonkk/k8s-pilot",
    "repo": "https://github.com/bourbonkk/k8s-pilot",
    "homepage": null,
    "docs": null,
    "endpoint": null
  },
  "summary": {
    "transport": [
      "unknown"
    ],
    "auth": "unknown",
    "installConfidence": "low",
    "verification": "unknown",
    "toolCount": null
  }
}
