{
  "id": "github-va99-napier-34b5cb69",
  "name": "va99/napier",
  "description": "Napier facilitates the installation of MCP servers through prompt-based commands, streamlining the setup process for npm and PyPi hosted servers.",
  "category": "Utilities & Helpers",
  "profileUrl": "https://tensorblock.co/mcp/github-va99-napier-34b5cb69",
  "badgeMarkdown": "[![Listed on TensorBlock MCP Index](https://img.shields.io/badge/TensorBlock-MCP%20Index-blue)](https://tensorblock.co/mcp/github-va99-napier-34b5cb69)",
  "links": {
    "primary": "https://github.com/va99/napier",
    "repo": "https://github.com/va99/napier",
    "homepage": null,
    "docs": null,
    "endpoint": null
  },
  "summary": {
    "transport": [
      "unknown"
    ],
    "auth": "unknown",
    "installConfidence": "low",
    "verification": "unknown",
    "toolCount": null
  }
}
