{
  "id": "github-chaminda360-weather-server-6644a271",
  "name": "chaminda360/weather-server",
  "description": "A TypeScript-based server offering weather data management and summarization through MCP protocols.",
  "category": "Location & Maps",
  "profileUrl": "https://tensorblock.co/mcp/github-chaminda360-weather-server-6644a271",
  "badgeMarkdown": "[![Listed on TensorBlock MCP Index](https://img.shields.io/badge/TensorBlock-MCP%20Index-blue)](https://tensorblock.co/mcp/github-chaminda360-weather-server-6644a271)",
  "links": {
    "primary": "https://github.com/chaminda360/weather-server",
    "repo": "https://github.com/chaminda360/weather-server",
    "homepage": null,
    "docs": null,
    "endpoint": null
  },
  "summary": {
    "transport": [
      "unknown"
    ],
    "auth": "unknown",
    "installConfidence": "low",
    "verification": "unknown",
    "toolCount": null
  }
}
