{
  "id": "github-jackkuo666-clinicaltrials-mcp-server-bee8daad",
  "name": "JackKuo666/ClinicalTrials-MCP-Server",
  "description": "Facilitates AI-driven searches and access to ClinicalTrials.gov data, enhancing health sciences research through a streamlined MCP interface.",
  "category": "Healthcare & Life Sciences",
  "profileUrl": "https://tensorblock.co/mcp/github-jackkuo666-clinicaltrials-mcp-server-bee8daad",
  "badgeMarkdown": "[![Listed on TensorBlock MCP Index](https://img.shields.io/badge/TensorBlock-MCP%20Index-blue)](https://tensorblock.co/mcp/github-jackkuo666-clinicaltrials-mcp-server-bee8daad)",
  "links": {
    "primary": "https://github.com/JackKuo666/ClinicalTrials-MCP-Server",
    "repo": "https://github.com/JackKuo666/ClinicalTrials-MCP-Server",
    "homepage": null,
    "docs": null,
    "endpoint": null
  },
  "summary": {
    "transport": [
      "unknown"
    ],
    "auth": "unknown",
    "installConfidence": "low",
    "verification": "unknown",
    "toolCount": null
  }
}
