{
  "id": "github-savethepolarbears-google-photos-mcp-d18249a8",
  "name": "savethepolarbears/google-photos-mcp",
  "description": "Facilitates AI assistants' access to Google Photos, enabling photo search and retrieval by content, date, and location.",
  "category": "Multimedia Processing",
  "profileUrl": "https://tensorblock.co/mcp/github-savethepolarbears-google-photos-mcp-d18249a8",
  "badgeMarkdown": "[![Listed on TensorBlock MCP Index](https://img.shields.io/badge/TensorBlock-MCP%20Index-blue)](https://tensorblock.co/mcp/github-savethepolarbears-google-photos-mcp-d18249a8)",
  "links": {
    "primary": "https://github.com/savethepolarbears/google-photos-mcp",
    "repo": "https://github.com/savethepolarbears/google-photos-mcp",
    "homepage": null,
    "docs": null,
    "endpoint": null
  },
  "summary": {
    "transport": [
      "unknown"
    ],
    "auth": "unknown",
    "installConfidence": "low",
    "verification": "unknown",
    "toolCount": null
  }
}
