{
  "id": "github-errajibadr-twilio-manager-mcp-acbdc404",
  "name": "errajibadr/twilio_manager_mcp",
  "description": "Manage Twilio resources through a standardized MCP interface, supporting subaccount management, phone number transfers, and regulatory bundle retrieval.",
  "category": "Communication & Messaging",
  "profileUrl": "https://tensorblock.co/mcp/github-errajibadr-twilio-manager-mcp-acbdc404",
  "badgeMarkdown": "[![Listed on TensorBlock MCP Index](https://img.shields.io/badge/TensorBlock-MCP%20Index-blue)](https://tensorblock.co/mcp/github-errajibadr-twilio-manager-mcp-acbdc404)",
  "links": {
    "primary": "https://github.com/errajibadr/twilio_manager_mcp",
    "repo": "https://github.com/errajibadr/twilio_manager_mcp",
    "homepage": null,
    "docs": null,
    "endpoint": null
  },
  "summary": {
    "transport": [
      "unknown"
    ],
    "auth": "unknown",
    "installConfidence": "low",
    "verification": "unknown",
    "toolCount": null
  }
}
