{
  "id": "github-ryanjoachim-mcp-rtfm-c65b583a",
  "name": "ryanjoachim/mcp-rtfm",
  "description": "MCP-RTFM transforms unreadable or non-existent documentation into an intelligent, searchable knowledge base with advanced content analysis and metadata generation.",
  "category": "Knowledge Management & Memory",
  "profileUrl": "https://tensorblock.co/mcp/github-ryanjoachim-mcp-rtfm-c65b583a",
  "badgeMarkdown": "[![Listed on TensorBlock MCP Index](https://img.shields.io/badge/TensorBlock-MCP%20Index-blue)](https://tensorblock.co/mcp/github-ryanjoachim-mcp-rtfm-c65b583a)",
  "links": {
    "primary": "https://github.com/ryanjoachim/mcp-rtfm",
    "repo": "https://github.com/ryanjoachim/mcp-rtfm",
    "homepage": null,
    "docs": null,
    "endpoint": null
  },
  "summary": {
    "transport": [
      "unknown"
    ],
    "auth": "unknown",
    "installConfidence": "low",
    "verification": "unknown",
    "toolCount": null
  }
}
