{
  "id": "github-bmorphism-anti-bullshit-mcp-server-6d614da5",
  "name": "bmorphism/anti-bullshit-mcp-server",
  "description": "Analyzes claims, validates sources, and detects manipulation using diverse epistemological frameworks.",
  "category": "Science & Research",
  "profileUrl": "https://tensorblock.co/mcp/github-bmorphism-anti-bullshit-mcp-server-6d614da5",
  "badgeMarkdown": "[![Listed on TensorBlock MCP Index](https://img.shields.io/badge/TensorBlock-MCP%20Index-blue)](https://tensorblock.co/mcp/github-bmorphism-anti-bullshit-mcp-server-6d614da5)",
  "links": {
    "primary": "https://github.com/bmorphism/anti-bullshit-mcp-server",
    "repo": "https://github.com/bmorphism/anti-bullshit-mcp-server",
    "homepage": null,
    "docs": null,
    "endpoint": null
  },
  "summary": {
    "transport": [
      "unknown"
    ],
    "auth": "unknown",
    "installConfidence": "low",
    "verification": "unknown",
    "toolCount": null
  }
}
