{
  "id": "github-jroakes-crawlnchat-3da3c429",
  "name": "jroakes/CrawlnChat",
  "description": "A versatile system for web crawling and AI-powered chat interfaces, integrating XML sitemap ingestion, vector embeddings, and multiple frontend options including MCP.",
  "category": "Browser Automation & Web Scraping",
  "profileUrl": "https://tensorblock.co/mcp/github-jroakes-crawlnchat-3da3c429",
  "badgeMarkdown": "[![Listed on TensorBlock MCP Index](https://img.shields.io/badge/TensorBlock-MCP%20Index-blue)](https://tensorblock.co/mcp/github-jroakes-crawlnchat-3da3c429)",
  "links": {
    "primary": "https://github.com/jroakes/CrawlnChat",
    "repo": "https://github.com/jroakes/CrawlnChat",
    "homepage": null,
    "docs": null,
    "endpoint": null
  },
  "summary": {
    "transport": [
      "unknown"
    ],
    "auth": "unknown",
    "installConfidence": "low",
    "verification": "unknown",
    "toolCount": null
  }
}
