{
  "id": "github-youqingkui-dify-service-1b6acf2e",
  "name": "youqingkui/dify_service",
  "description": "A server that manages note storage and summarization with custom URI schemes and prompt tools.",
  "category": "Location & Maps",
  "profileUrl": "https://tensorblock.co/mcp/github-youqingkui-dify-service-1b6acf2e",
  "badgeMarkdown": "[![Listed on TensorBlock MCP Index](https://img.shields.io/badge/TensorBlock-MCP%20Index-blue)](https://tensorblock.co/mcp/github-youqingkui-dify-service-1b6acf2e)",
  "links": {
    "primary": "https://github.com/youqingkui/dify_service",
    "repo": "https://github.com/youqingkui/dify_service",
    "homepage": null,
    "docs": null,
    "endpoint": null
  },
  "summary": {
    "transport": [
      "unknown"
    ],
    "auth": "unknown",
    "installConfidence": "low",
    "verification": "unknown",
    "toolCount": null
  }
}
