{
  "id": "github-leonardsellem-n8n-mcp-server-d659b47e",
  "name": "leonardsellem/n8n-mcp-server",
  "description": "Facilitates AI-driven management of n8n workflows through natural language interactions.",
  "category": "Developer Productivity & Utilities",
  "profileUrl": "https://tensorblock.co/mcp/github-leonardsellem-n8n-mcp-server-d659b47e",
  "badgeMarkdown": "[![Listed on TensorBlock MCP Index](https://img.shields.io/badge/TensorBlock-MCP%20Index-blue)](https://tensorblock.co/mcp/github-leonardsellem-n8n-mcp-server-d659b47e)",
  "links": {
    "primary": "https://github.com/leonardsellem/n8n-mcp-server",
    "repo": "https://github.com/leonardsellem/n8n-mcp-server",
    "homepage": null,
    "docs": null,
    "endpoint": null
  },
  "summary": {
    "transport": [
      "unknown"
    ],
    "auth": "unknown",
    "installConfidence": "low",
    "verification": "unknown",
    "toolCount": null
  }
}
