{
  "id": "github-shibley-apistatuscheck-13f09948",
  "name": "shibley/apistatuscheck",
  "description": "Monitors real-time API status across 250+ popular services, providing outage detection, historical uptime data, and status page aggregation through the Model Context Protocol.",
  "category": "Monitoring & Observability",
  "profileUrl": "https://tensorblock.co/mcp/github-shibley-apistatuscheck-13f09948",
  "badgeMarkdown": "[![Listed on TensorBlock MCP Index](https://img.shields.io/badge/TensorBlock-MCP%20Index-blue)](https://tensorblock.co/mcp/github-shibley-apistatuscheck-13f09948)",
  "links": {
    "primary": "https://github.com/shibley/apistatuscheck",
    "repo": "https://github.com/shibley/apistatuscheck",
    "homepage": null,
    "docs": null,
    "endpoint": null
  },
  "summary": {
    "transport": [
      "unknown"
    ],
    "auth": "unknown",
    "installConfidence": "low",
    "verification": "unknown",
    "toolCount": null
  }
}
