{
  "id": "github-piplabs-story-mcp-hub-abfa73cb",
  "name": "piplabs/story-mcp-hub",
  "description": "Facilitates AI agent interactions with Story Protocol's ecosystem through blockchain data queries and SDK interactions.",
  "category": "Knowledge Management & Memory",
  "profileUrl": "https://tensorblock.co/mcp/github-piplabs-story-mcp-hub-abfa73cb",
  "badgeMarkdown": "[![Listed on TensorBlock MCP Index](https://img.shields.io/badge/TensorBlock-MCP%20Index-blue)](https://tensorblock.co/mcp/github-piplabs-story-mcp-hub-abfa73cb)",
  "links": {
    "primary": "https://github.com/piplabs/story-mcp-hub",
    "repo": "https://github.com/piplabs/story-mcp-hub",
    "homepage": null,
    "docs": null,
    "endpoint": null
  },
  "summary": {
    "transport": [
      "unknown"
    ],
    "auth": "unknown",
    "installConfidence": "low",
    "verification": "unknown",
    "toolCount": null
  }
}
