{
  "id": "xpoz-ai-ed7b7a81",
  "name": "Xpoz MCP",
  "description": "Remote-only social media MCP server for Twitter/X, Instagram, and TikTok data & insights. 1.5B+ posts indexed. No installation required - just add endpoint URL (https://mcp.xpoz.ai). No API keys needed.",
  "category": "Social Media & Content Platforms",
  "profileUrl": "https://tensorblock.co/mcp/xpoz-ai-ed7b7a81",
  "badgeMarkdown": "[![Listed on TensorBlock MCP Index](https://img.shields.io/badge/TensorBlock-MCP%20Index-blue)](https://tensorblock.co/mcp/xpoz-ai-ed7b7a81)",
  "links": {
    "primary": "https://xpoz.ai",
    "repo": null,
    "homepage": "https://xpoz.ai",
    "docs": null,
    "endpoint": "https://mcp.xpoz.ai"
  },
  "summary": {
    "transport": [
      "unknown"
    ],
    "auth": "none",
    "installConfidence": "low",
    "verification": "unknown",
    "toolCount": null
  }
}
